scrapi_reddit/__init__.py
scrapi_reddit/cli.py
scrapi_reddit/core.py
scrapi_reddit-0.2.2.dist-info/licenses/LICENSE
scrapi_reddit-0.2.2.dist-info/METADATA
scrapi_reddit-0.2.2.dist-info/WHEEL
scrapi_reddit-0.2.2.dist-info/entry_points.txt
scrapi_reddit-0.2.2.dist-info/top_level.txt
scrapi_reddit-0.2.2.dist-info/RECORD
