Metadata-Version: 2.4
Name: scrapi-reddit
Version: 0.2.2
Summary: Zero-auth Reddit scraper CLI and library
Author: Rodney Keilson
License-Expression: MIT
Project-URL: Homepage, https://github.com/rodneykeilson/ScrapiReddit
Requires-Python: >=3.9
License-File: LICENSE
Requires-Dist: requests>=2.31
Requires-Dist: tomli>=2.0; python_version < "3.11"
Dynamic: license-file
